Workbook

Sheet Premissas
A1: Semanas por mês (52/12) | B1: =52/12
A2: Custo por crédito IA (R$, com cache) | B2: 0.02586
A3: Custo médio por consulta (R$) | B3: 0.6472
A4: Imposto (% do preço) | B4: 0.06
A5: Cartão % (Asaas) | B5: 0.0299
A6: Cartão fixo (R$) | B6: 0.49
A7: Outros custos/conta/mês (R$) | B7: 5
A8: Margem mínima exigida | B8: 0.5
A9: Regra: créditos = (tokens entrada totais + 5 × tokens saída) ÷ 2.500 | B9: (entrada totais = input + cache_creation + cache_read)

Sheet Planos Semanais
A1: Item | B1: Trial 14 dias | C1: Starter | D1: Pro | E1: Business
A2: Preço mensal (R$) | B2: 0 | C2: 97 | D2: 197 | E2: 397
A3: Usuários | B3: 1 | C3: 1 | D3: 5 | E3: 15
A4: Créditos IA / semana | B4: 50 | C4: 150 | D4: 300 | E4: 700
A5: Consultas / semana | B5: 2 | C5: 5 | D5: 10 | E5: 20
A6: Créditos IA / mês (equiv.) | B6: =B4*Premissas!$B$1 | C6: =C4*Premissas!$B$1 | D6: =D4*Premissas!$B$1 | E6: =E4*Premissas!$B$1
A7: Consultas / mês (equiv.) | B7: =B5*Premissas!$B$1 | C7: =C5*Premissas!$B$1 | D7: =D5*Premissas!$B$1 | E7: =E5*Premissas!$B$1
A8: Custo IA / semana | B8: =B4*Premissas!$B$2 | C8: =C4*Premissas!$B$2 | D8: =D4*Premissas!$B$2 | E8: =E4*Premissas!$B$2
A9: Custo consultas / semana | B9: =B5*Premissas!$B$3 | C9: =C5*Premissas!$B$3 | D9: =D5*Premissas!$B$3 | E9: =E5*Premissas!$B$3
A10: Custo variável / mês @100% uso | B10: =(B8+B9)*Premissas!$B$1 | C10: =(C8+C9)*Premissas!$B$1 | D10: =(D8+D9)*Premissas!$B$1 | E10: =(E8+E9)*Premissas!$B$1
A11: Custos fixos/mês (imposto+cartão+outros) | B11: =IF(B2=0,0,B2*Premissas!$B$4+B2*Premissas!$B$5+Premissas!$B$6+Premissas!$B$7) | C11: =IF(C2=0,0,C2*Premissas!$B$4+C2*Premissas!$B$5+Premissas!$B$6+Premissas!$B$7) | D11: =IF(D2=0,0,D2*Premissas!$B$4+D2*Premissas!$B$5+Premissas!$B$6+Premissas!$B$7) | E11: =IF(E2=0,0,E2*Premissas!$B$4+E2*Premissas!$B$5+Premissas!$B$6+Premissas!$B$7)
A12: Margem @100% uso | B12: =IF(B2=0,"n/a (trial)",(B2-B10-B11)/B2) | C12: =IF(C2=0,"n/a (trial)",(C2-C10-C11)/C2) | D12: =IF(D2=0,"n/a (trial)",(D2-D10-D11)/D2) | E12: =IF(E2=0,"n/a (trial)",(E2-E10-E11)/E2)
A13: Margem @50% uso | B13: =IF(B2=0,"n/a (trial)",(B2-B10*0.5-B11)/B2) | C13: =IF(C2=0,"n/a (trial)",(C2-C10*0.5-C11)/C2) | D13: =IF(D2=0,"n/a (trial)",(D2-D10*0.5-D11)/D2) | E13: =IF(E2=0,"n/a (trial)",(E2-E10*0.5-E11)/E2)
A14: Atende ≥ margem mínima? | B14: =IF(B2=0,"custo do trial (14d): R$ "&ROUND((B8+B9)*2,2),IF(B12>=Premissas!$B$8,"SIM","NÃO")) | C14: =IF(C2=0,"custo do trial (14d): R$ "&ROUND((C8+C9)*2,2),IF(C12>=Premissas!$B$8,"SIM","NÃO")) | D14: =IF(D2=0,"custo do trial (14d): R$ "&ROUND((D8+D9)*2,2),IF(D12>=Premissas!$B$8,"SIM","NÃO")) | E14: =IF(E2=0,"custo do trial (14d): R$ "&ROUND((E8+E9)*2,2),IF(E12>=Premissas!$B$8,"SIM","NÃO"))
